autonet_arista/__init__.py
autonet_arista/__version__.py
autonet_arista/eos/__init__.py
autonet_arista/eos/const.py
autonet_arista/eos/eos_driver.py
autonet_arista/eos/exceptions.py
autonet_arista/eos/util.py
autonet_arista/eos/tasks/__init__.py
autonet_arista/eos/tasks/common.py
autonet_arista/eos/tasks/interface.py
autonet_arista/eos/tasks/lag.py
autonet_arista/eos/tasks/vlan.py
autonet_arista/eos/tasks/vrf.py
autonet_arista/eos/tasks/vxlan.py
autonet_arista/eos/tests/__init__.py
autonet_arista/eos/tests/conftest.py
autonet_arista/eos/tests/test_eos_driver.py
autonet_arista/eos/tests/test_util.py
autonet_arista-0.2.1.dist-info/LICENSE.txt
autonet_arista-0.2.1.dist-info/METADATA
autonet_arista-0.2.1.dist-info/WHEEL
autonet_arista-0.2.1.dist-info/entry_points.txt
autonet_arista-0.2.1.dist-info/top_level.txt
autonet_arista-0.2.1.dist-info/RECORD
